hack4u/__init__.py
hack4u/courses.py
hack4u/utils.py
sirus_paquete-0.1.0.dist-info/METADATA
sirus_paquete-0.1.0.dist-info/WHEEL
sirus_paquete-0.1.0.dist-info/top_level.txt
sirus_paquete-0.1.0.dist-info/RECORD
