Metadata-Version: 2.4
Name: sirus_paquete
Version: 0.1.0
Summary: Consultar cursos de la academia Hack4u de S4vitar
Home-page: https://hack4u.io
Author: SIrus
Dynamic: author
Dynamic: description
Dynamic: description-content-type
Dynamic: home-page
Dynamic: summary
